qvecopt_provider/__init__.py
qvecopt_provider/backend.py
qvecopt_provider/job.py
qvecopt_provider/provider.py
qvecopt_provider/result.py
qvecopt_provider-0.2.1.dist-info/licenses/LICENSE
qvecopt_provider-0.2.1.dist-info/METADATA
qvecopt_provider-0.2.1.dist-info/WHEEL
qvecopt_provider-0.2.1.dist-info/top_level.txt
qvecopt_provider-0.2.1.dist-info/RECORD
