Metadata-Version: 2.4
Name: qvecopt_provider
Version: 0.2.1
Summary: QVecOpt Provider 是一个用于集成 Qiskit 与 QVecOpt 后端的 Python 包
Author-email: aurawing <zhangxusmall@gmail.com>
License: MIT
Project-URL: Homepage, https://gitee.com/aurawing/qvecopt_provider
Project-URL: Bug Tracker, https://gitee.com/aurawing/qvecopt_provider/issues
Requires-Python: >=3.7
License-File: LICENSE
Requires-Dist: requests>=2.0
Requires-Dist: qiskit>=2.0.0
Dynamic: license-file
